pyqt_find_replace_text_widget/__init__.py
pyqt_find_replace_text_widget/findReplaceTextWidget.py
pyqt_find_replace_text_widget/replaceTextWidget.py
pyqt_find_replace_text_widget/ico/__init__.py
pyqt_find_replace_text_widget/ico/close.svg
pyqt_find_replace_text_widget/ico/swap_v.svg
pyqt_find_replace_text_widget-0.0.14.dist-info/LICENSE
pyqt_find_replace_text_widget-0.0.14.dist-info/METADATA
pyqt_find_replace_text_widget-0.0.14.dist-info/WHEEL
pyqt_find_replace_text_widget-0.0.14.dist-info/top_level.txt
pyqt_find_replace_text_widget-0.0.14.dist-info/RECORD
