Metadata-Version: 2.1
Name: pyqt-find-replace-text-widget
Version: 0.0.14
Summary: PyQt widget which can find and replace text in the QTextEdit/QTextBrowser
Home-page: https://github.com/yjg30737/pyqt-find-replace-text-widget.git
Author: Jung Gyu Yoon
Author-email: yjg30737@gmail.com
License: MIT
License-File: LICENSE
Requires-Dist: PyQt5 (>=5.8)
Requires-Dist: pyqt-find-text-widget (>=0.0.1)
